r00adb/__init__.py
r00adb/adbase.py
r00adb/main.py
r00adb/sshbase.py
r00adb/executors/__init__.py
r00adb/executors/default.py
r00adb/executors/sdk28/__init__.py
r00adb/executors/sdk28/adb.py
r00adb/executors/sdk28/ssh.py
r00adb/helpers/__init__.py
r00adb/helpers/constants.py
r00adb/helpers/exceptions.py
r00adb/helpers/utils.py
r00adb/modules/__init__.py
r00adb/modules/_speed_test.py
r00adb/modules/twrp.py
r00adb/transports/__init__.py
r00adb/transports/connection.py
r00adb/transports/custom_agent.c
r00adb/transports/custom_agent.py
r00adb-0.1.3.dist-info/METADATA
r00adb-0.1.3.dist-info/WHEEL
r00adb-0.1.3.dist-info/RECORD
