Metadata-Version: 2.4
Name: r00adb
Version: 0.1.3
Requires-Python: >=3.10
Requires-Dist: cryptography
Requires-Dist: dsnparse
Requires-Dist: pycryptodome
Requires-Dist: r00pykit
Requires-Dist: rsa
